enbios2/__init__.py
enbios2/const.py
enbios2/init_appdir.py
enbios2/settings.py
enbios2/analyse/__init__.py
enbios2/analyse/ana_experiment.py
enbios2/analyse/callipope_ana.py
enbios2/analyse/const.py
enbios2/analyse/experiment_exporter.py
enbios2/analyse/util.py
enbios2/base/__init__.py
enbios2/base/databases.py
enbios2/base/db_fields.py
enbios2/base/db_models.py
enbios2/base/experiment.py
enbios2/base/experiment_io.py
enbios2/base/scenario.py
enbios2/base/stacked_MultiLCA.py
enbios2/base/unit_registry.py
enbios2/bw2/__init__.py
enbios2/bw2/bw_autoimporter.py
enbios2/bw2/experiment_multiLCA.py
enbios2/bw2/extract_from_xml.py
enbios2/bw2/project_index.py
enbios2/bw2/util.py
enbios2/demos/__init__.py
enbios2/demos/demo.py
enbios2/demos/tests.py
enbios2/dev/__init__.py
enbios2/dev/create_experiment_schema.py
enbios2/dev/evoinvent_dbs.py
enbios2/dev/pull_docs.py
enbios2/ecoinvent/__init__.py
enbios2/ecoinvent/ecoinvent_index.py
enbios2/ecoinvent/ecoinvent_resolved_dataset_db.py
enbios2/ecoinvent/spatial.py
enbios2/experiment/__init__.py
enbios2/experiment/activity_search.py
enbios2/experiment/ai_lcia.py
enbios2/experiment/bw2sigma.py
enbios2/experiment/bw_manipulation.py
enbios2/experiment/characterizations.py
enbios2/experiment/class_static_me.py
enbios2/experiment/comp_numba.py
enbios2/experiment/create_networkx.py
enbios2/experiment/dot2bw.py
enbios2/experiment/fast_tree.py
enbios2/experiment/promt_toolkit_checker.py
enbios2/experiment/schema_builder.py
enbios2/experiment/spold2json.py
enbios2/experiment/starcoder.py
enbios2/experiment/sum_hierarchy.py
enbios2/experiment/tree_transformer.py
enbios2/experiment/util.py
enbios2/experiment/bw2/__init__.py
enbios2/experiment/bw2/excel_importer.py
enbios2/experiment/bw2/multiLCA.py
enbios2/experiment/bw2/non_linear_methods.py
enbios2/experiment/bw_vector_db/__init__.py
enbios2/experiment/bw_vector_db/cluster.py
enbios2/experiment/bw_vector_db/create_vectors.py
enbios2/experiment/bw_vector_db/plotting.py
enbios2-0.1.5.dist-info/LICENSE
enbios2-0.1.5.dist-info/METADATA
enbios2-0.1.5.dist-info/WHEEL
enbios2-0.1.5.dist-info/top_level.txt
enbios2-0.1.5.dist-info/RECORD
