Metadata-Version: 2.1
Name: enbios2
Version: 0.1.5
Summary: Enbios 2
Author: Ramin Soleymani
License: MIT License
Project-URL: Homepage, https://github.com/LIVENlab/enbios
Project-URL: Bug Tracker, https://github.com/LIVENlab/enbios/issues
Classifier: Development Status :: 4 - Beta
Classifier: Programming Language :: Python
Classifier: Intended Audience :: Developers
Classifier: Intended Audience :: Science/Research
Classifier: Operating System :: MacOS :: MacOS X
Classifier: Operating System :: Microsoft :: Windows
Classifier: Operating System :: POSIX :: Linux
Classifier: Programming Language :: Python
Classifier: Programming Language :: Python :: 3.9
Classifier: Programming Language :: Python :: 3.10
Classifier: Programming Language :: Python :: 3.11
Classifier: Programming Language :: Python :: 3 :: Only
Classifier: Topic :: Scientific/Engineering :: Information Analysis
Classifier: Topic :: Scientific/Engineering :: Mathematics
Classifier: Topic :: Scientific/Engineering :: Visualization
Classifier: Typing :: Typed
Requires-Python: >=3.9
License-File: LICENSE
Requires-Dist: annotated-types ==0.5.0
Requires-Dist: appdirs ==1.4.4
Requires-Dist: asteval ==0.9.31
Requires-Dist: astunparse ==1.6.3
Requires-Dist: brightway25 ==1.0.6
Requires-Dist: bw-migrations ==0.2
Requires-Dist: bw-processing ==0.8.3
Requires-Dist: bw2analyzer ==0.11.5
Requires-Dist: bw2calc ==2.0.dev13
Requires-Dist: bw2data ==4.0.dev19
Requires-Dist: bw2io ==0.9.dev19
Requires-Dist: bw2parameters ==1.1.0
Requires-Dist: certifi ==2023.7.22
Requires-Dist: charset-normalizer ==3.2.0
Requires-Dist: contourpy ==1.1.0
Requires-Dist: cycler ==0.11.0
Requires-Dist: et-xmlfile ==1.1.0
Requires-Dist: fonttools ==4.41.1
Requires-Dist: fs ==2.4.16
Requires-Dist: idna ==3.4
Requires-Dist: importlib-resources ==6.0.0
Requires-Dist: kiwisolver ==1.4.4
Requires-Dist: lxml ==4.9.3
Requires-Dist: matplotlib ==3.7.2
Requires-Dist: matrix-utils ==0.2.5
Requires-Dist: mrio-common-metadata ==0.2.1
Requires-Dist: numpy ==1.25.1
Requires-Dist: openpyxl ==3.1.2
Requires-Dist: packaging ==23.1
Requires-Dist: pandas ==2.0.3
Requires-Dist: peewee ==3.16.2
Requires-Dist: Pillow ==10.0.0
Requires-Dist: Pint ==0.22
Requires-Dist: platformdirs ==3.9.1
Requires-Dist: pydantic ==2.1.1
Requires-Dist: pydantic-core ==2.4.0
Requires-Dist: pyparsing ==3.0.9
Requires-Dist: PyPrind ==2.11.3
Requires-Dist: python-dateutil ==2.8.2
Requires-Dist: pytz ==2023.3
Requires-Dist: pyxlsb ==1.0.10
Requires-Dist: PyYAML ==6.0.1
Requires-Dist: requests ==2.31.0
Requires-Dist: scipy ==1.11.1
Requires-Dist: six ==1.16.0
Requires-Dist: stats-arrays ==0.6.5
Requires-Dist: tabulate ==0.9.0
Requires-Dist: tqdm ==4.65.0
Requires-Dist: typing-extensions ==4.7.1
Requires-Dist: tzdata ==2023.3
Requires-Dist: Unidecode ==1.3.6
Requires-Dist: urllib3 ==2.0.4
Requires-Dist: voluptuous ==0.13.1
Requires-Dist: Whoosh ==2.7.4
Requires-Dist: wrapt ==1.15.0
Requires-Dist: xlrd ==2.0.1
Requires-Dist: XlsxWriter ==3.1.2
Requires-Dist: xmltodict ==0.13.0
Requires-Dist: zipp ==3.16.2
Provides-Extra: test
Requires-Dist: pytest ==7.3.2 ; extra == 'test'
